{
    "inlet_throats": [
        0,
        5,
        10,
        15,
        19,
        24
    ],
    "outlet_throats": [
        4,
        9,
        14,
        18,
        23,
        27
    ],
    "polygons": {
        "0": [
            [
                [
                    0.00015370286675591284,
                    -3.353131001040819e-05,
                    0
                ],
                [
                    0.00015370286675591284,
                    -3.353131001040819e-05,
                    6.72e-05
                ],
                [
                    0,
                    -2.093131001040819e-05,
                    0
                ],
                [
                    0,
                    -2.093131001040819e-05,
                    6.72e-05
                ]
            ],
            [
                [
                    0,
                    2.093131001040819e-05,
                    0
                ],
                [
                    0,
                    2.093131001040819e-05,
                    6.72e-05
                ],
                [
                    0.00015709713324408713,
                    8.331310010408192e-06,
                    0
                ],
                [
                    0.00015709713324408713,
                    8.331310010408192e-06,
                    6.72e-05
                ]
            ]
        ],
        "1": [
            [
                [
                    0.00036272383890020025,
                    1.7355085383074806e-06,
                    0
                ],
                [
                    0.00036272383890020025,
                    1.7355085383074806e-06,
                    6.72e-05
                ],
                [
                    0.00014453550853830746,
                    -2.672383890020027e-05,
                    0
                ],
                [
                    0.00014453550853830746,
                    -2.672383890020027e-05,
                    6.72e-05
                ]
            ],
            [
                [
                    0.00014127616109979973,
                    -1.7355085383074806e-06,
                    0
                ],
                [
                    0.00014127616109979973,
                    -1.7355085383074806e-06,
                    6.72e-05
                ],
                [
                    0.00035946449146169245,
                    2.672383890020027e-05,
                    0
                ],
                [
                    0.00035946449146169245,
                    2.672383890020027e-05,
                    6.72e-05
                ]
            ]
        ],
        "2": [
            [
                [
                    0.00048775050798791,
                    -3.328045473517667e-05,
                    0
                ],
                [
                    0.00048775050798791,
                    -3.328045473517667e-05,
                    6.72e-05
                ],
                [
                    0.00034495050798790994,
                    -8.080454735176672e-06,
                    0
                ],
                [
                    0.00034495050798790994,
                    -8.080454735176672e-06,
                    6.72e-05
                ]
            ],
            [
                [
                    0.00035224949201209,
                    3.328045473517667e-05,
                    0
                ],
                [
                    0.00035224949201209,
                    3.328045473517667e-05,
                    6.72e-05
                ],
                [
                    0.00049504949201209,
                    8.080454735176672e-06,
                    0
                ],
                [
                    0.00049504949201209,
                    8.080454735176672e-06,
                    6.72e-05
                ]
            ]
        ],
        "3": [
            [
                [
                    0.0006762,
                    -2.9399999999999996e-05,
                    0
                ],
                [
                    0.0006762,
                    -2.9399999999999996e-05,
                    6.72e-05
                ],
                [
                    0.0004914,
                    -2.9399999999999996e-05,
                    0
                ],
                [
                    0.0004914,
                    -2.9399999999999996e-05,
                    6.72e-05
                ]
            ],
            [
                [
                    0.0004914,
                    4.2000000000000004e-06,
                    0
                ],
                [
                    0.0004914,
                    4.2000000000000004e-06,
                    6.72e-05
                ],
                [
                    0.0006762,
                    4.2000000000000004e-06,
                    0
                ],
                [
                    0.0006762,
                    4.2000000000000004e-06,
                    6.72e-05
                ]
            ]
        ],
        "4": [
            [
                [
                    0.0008399999999999999,
                    -2.0949077117560637e-05,
                    0
                ],
                [
                    0.0008399999999999999,
                    -2.0949077117560637e-05,
                    6.72e-05
                ],
                [
                    0.0006608615635198298,
                    -3.3549077117560635e-05,
                    0
                ],
                [
                    0.0006608615635198298,
                    -3.3549077117560635e-05,
                    6.72e-05
                ]
            ],
            [
                [
                    0.0006579384364801702,
                    8.34907711756064e-06,
                    0
                ],
                [
                    0.0006579384364801702,
                    8.34907711756064e-06,
                    6.72e-05
                ],
                [
                    0.0008399999999999999,
                    2.0949077117560637e-05,
                    0
                ],
                [
                    0.0008399999999999999,
                    2.0949077117560637e-05,
                    6.72e-05
                ]
            ]
        ],
        "5": [
            [
                [
                    0.00015370286675591284,
                    0.0001344686899895918,
                    0
                ],
                [
                    0.00015370286675591284,
                    0.0001344686899895918,
                    6.72e-05
                ],
                [
                    0,
                    0.0001470686899895918,
                    0
                ],
                [
                    0,
                    0.0001470686899895918,
                    6.72e-05
                ]
            ],
            [
                [
                    0,
                    0.00018893131001040817,
                    0
                ],
                [
                    0,
                    0.00018893131001040817,
                    6.72e-05
                ],
                [
                    0.00015709713324408713,
                    0.00017633131001040816,
                    0
                ],
                [
                    0.00015709713324408713,
                    0.00017633131001040816,
                    6.72e-05
                ]
            ]
        ],
        "6": [
            [
                [
                    0.0003513161228654231,
                    0.00015977639136508935,
                    0
                ],
                [
                    0.0003513161228654231,
                    0.00015977639136508935,
                    6.72e-05
                ],
                [
                    0.00014562195768447672,
                    0.00013294671764583547,
                    0
                ],
                [
                    0.00014562195768447672,
                    0.00013294671764583547,
                    6.72e-05
                ]
            ],
            [
                [
                    0.00014018971195363047,
                    0.00017459393491565676,
                    0
                ],
                [
                    0.00014018971195363047,
                    0.00017459393491565676,
                    6.72e-05
                ],
                [
                    0.00034588387713457684,
                    0.00020142360863491064,
                    0
                ],
                [
                    0.00034588387713457684,
                    0.00020142360863491064,
                    6.72e-05
                ]
            ]
        ],
        "7": [
            [
                [
                    0.0005166,
                    0.0001596,
                    0
                ],
                [
                    0.0005166,
                    0.0001596,
                    6.72e-05
                ],
                [
                    0.00034859999999999996,
                    0.0001596,
                    0
                ],
                [
                    0.00034859999999999996,
                    0.0001596,
                    6.72e-05
                ]
            ],
            [
                [
                    0.00034859999999999996,
                    0.0002016,
                    0
                ],
                [
                    0.00034859999999999996,
                    0.0002016,
                    6.72e-05
                ],
                [
                    0.0005166,
                    0.0002016,
                    0
                ],
                [
                    0.0005166,
                    0.0002016,
                    6.72e-05
                ]
            ]
        ],
        "8": [
            [
                [
                    0.00065575050798791,
                    0.0001347195452648233,
                    0
                ],
                [
                    0.00065575050798791,
                    0.0001347195452648233,
                    6.72e-05
                ],
                [
                    0.00051295050798791,
                    0.00015991954526482332,
                    0
                ],
                [
                    0.00051295050798791,
                    0.00015991954526482332,
                    6.72e-05
                ]
            ],
            [
                [
                    0.00052024949201209,
                    0.00020128045473517668,
                    0
                ],
                [
                    0.00052024949201209,
                    0.00020128045473517668,
                    6.72e-05
                ],
                [
                    0.00066304949201209,
                    0.00017608045473517666,
                    0
                ],
                [
                    0.00066304949201209,
                    0.00017608045473517666,
                    6.72e-05
                ]
            ]
        ],
        "9": [
            [
                [
                    0.0008399999999999999,
                    0.00014705092288243936,
                    0
                ],
                [
                    0.0008399999999999999,
                    0.00014705092288243936,
                    6.72e-05
                ],
                [
                    0.0006608615635198298,
                    0.00013445092288243935,
                    0
                ],
                [
                    0.0006608615635198298,
                    0.00013445092288243935,
                    6.72e-05
                ]
            ],
            [
                [
                    0.0006579384364801702,
                    0.00017634907711756062,
                    0
                ],
                [
                    0.0006579384364801702,
                    0.00017634907711756062,
                    6.72e-05
                ],
                [
                    0.0008399999999999999,
                    0.00018894907711756062,
                    0
                ],
                [
                    0.0008399999999999999,
                    0.00018894907711756062,
                    6.72e-05
                ]
            ]
        ],
        "10": [
            [
                [
                    0.0001820615635198298,
                    0.00032765092288243933,
                    0
                ],
                [
                    0.0001820615635198298,
                    0.00032765092288243933,
                    6.72e-05
                ],
                [
                    0,
                    0.00031505092288243935,
                    0
                ],
                [
                    0,
                    0.00031505092288243935,
                    6.72e-05
                ]
            ],
            [
                [
                    0,
                    0.0003569490771175606,
                    0
                ],
                [
                    0,
                    0.0003569490771175606,
                    6.72e-05
                ],
                [
                    0.0001791384364801702,
                    0.0003695490771175606,
                    0
                ],
                [
                    0.0001791384364801702,
                    0.0003695490771175606,
                    6.72e-05
                ]
            ]
        ],
        "11": [
            [
                [
                    0.00031975050798791003,
                    0.0003027195452648233,
                    0
                ],
                [
                    0.00031975050798791003,
                    0.0003027195452648233,
                    6.72e-05
                ],
                [
                    0.00016445634280696361,
                    0.0003295492189840772,
                    0
                ],
                [
                    0.00016445634280696361,
                    0.0003295492189840772,
                    6.72e-05
                ]
            ],
            [
                [
                    0.0001717553268311436,
                    0.00037091012845443053,
                    0
                ],
                [
                    0.0001717553268311436,
                    0.00037091012845443053,
                    6.72e-05
                ],
                [
                    0.00032704949201208997,
                    0.0003440804547351767,
                    0
                ],
                [
                    0.00032704949201208997,
                    0.0003440804547351767,
                    6.72e-05
                ]
            ]
        ],
        "12": [
            [
                [
                    0.0004914,
                    0.0003024,
                    0
                ],
                [
                    0.0004914,
                    0.0003024,
                    6.72e-05
                ],
                [
                    0.0003234,
                    0.0003024,
                    0
                ],
                [
                    0.0003234,
                    0.0003024,
                    6.72e-05
                ]
            ],
            [
                [
                    0.0003234,
                    0.0003444,
                    0
                ],
                [
                    0.0003234,
                    0.0003444,
                    6.72e-05
                ],
                [
                    0.0004914,
                    0.0003444,
                    0
                ],
                [
                    0.0004914,
                    0.0003444,
                    6.72e-05
                ]
            ]
        ],
        "13": [
            [
                [
                    0.0006873161228654231,
                    0.0003277763913650893,
                    0
                ],
                [
                    0.0006873161228654231,
                    0.0003277763913650893,
                    6.72e-05
                ],
                [
                    0.0004941161228654232,
                    0.00030257639136508935,
                    0
                ],
                [
                    0.0004941161228654232,
                    0.00030257639136508935,
                    6.72e-05
                ]
            ],
            [
                [
                    0.0004886838771345768,
                    0.00034422360863491065,
                    0
                ],
                [
                    0.0004886838771345768,
                    0.00034422360863491065,
                    6.72e-05
                ],
                [
                    0.0006818838771345768,
                    0.0003694236086349106,
                    0
                ],
                [
                    0.0006818838771345768,
                    0.0003694236086349106,
                    6.72e-05
                ]
            ]
        ],
        "14": [
            [
                [
                    0.0008399999999999999,
                    0.0003192549519916734,
                    0
                ],
                [
                    0.0008399999999999999,
                    0.0003192549519916734,
                    6.72e-05
                ],
                [
                    0.0006664972453964037,
                    0.0003304972453964037,
                    0
                ],
                [
                    0.0006664972453964037,
                    0.0003304972453964037,
                    6.72e-05
                ]
            ],
            [
                [
                    0.0006692126585869431,
                    0.0003639873414130568,
                    0
                ],
                [
                    0.0006692126585869431,
                    0.0003639873414130568,
                    6.72e-05
                ],
                [
                    0.0008399999999999999,
                    0.00035274504800832655,
                    0
                ],
                [
                    0.0008399999999999999,
                    0.00035274504800832655,
                    6.72e-05
                ]
            ]
        ],
        "15": [
            [
                [
                    0.00015370286675591284,
                    0.0004704686899895918,
                    0
                ],
                [
                    0.00015370286675591284,
                    0.0004704686899895918,
                    6.72e-05
                ],
                [
                    0,
                    0.0004830686899895918,
                    0
                ],
                [
                    0,
                    0.0004830686899895918,
                    6.72e-05
                ]
            ],
            [
                [
                    0,
                    0.0005249313100104082,
                    0
                ],
                [
                    0,
                    0.0005249313100104082,
                    6.72e-05
                ],
                [
                    0.00015709713324408713,
                    0.0005123313100104082,
                    0
                ],
                [
                    0.00015709713324408713,
                    0.0005123313100104082,
                    6.72e-05
                ]
            ]
        ],
        "16": [
            [
                [
                    0.0003234,
                    0.00047880000000000004,
                    0
                ],
                [
                    0.0003234,
                    0.00047880000000000004,
                    6.72e-05
                ],
                [
                    0.00014279999999999997,
                    0.00047880000000000004,
                    0
                ],
                [
                    0.00014279999999999997,
                    0.00047880000000000004,
                    6.72e-05
                ]
            ],
            [
                [
                    0.00014279999999999997,
                    0.000504,
                    0
                ],
                [
                    0.00014279999999999997,
                    0.000504,
                    6.72e-05
                ],
                [
                    0.0003234,
                    0.000504,
                    0
                ],
                [
                    0.0003234,
                    0.000504,
                    6.72e-05
                ]
            ]
        ],
        "17": [
            [
                [
                    0.0004914,
                    0.00047880000000000004,
                    0
                ],
                [
                    0.0004914,
                    0.00047880000000000004,
                    6.72e-05
                ],
                [
                    0.0003234,
                    0.00047880000000000004,
                    0
                ],
                [
                    0.0003234,
                    0.00047880000000000004,
                    6.72e-05
                ]
            ],
            [
                [
                    0.0003234,
                    0.000504,
                    0
                ],
                [
                    0.0003234,
                    0.000504,
                    6.72e-05
                ],
                [
                    0.0004914,
                    0.000504,
                    0
                ],
                [
                    0.0004914,
                    0.000504,
                    6.72e-05
                ]
            ]
        ],
        "18": [
            [
                [
                    0.0008399999999999999,
                    0.00048725495199167343,
                    0
                ],
                [
                    0.0008399999999999999,
                    0.00048725495199167343,
                    6.72e-05
                ],
                [
                    0.0006832422934047302,
                    0.0004998549519916734,
                    0
                ],
                [
                    0.0006832422934047302,
                    0.0004998549519916734,
                    6.72e-05
                ]
            ],
            [
                [
                    0.0006859577065952697,
                    0.0005333450480083265,
                    0
                ],
                [
                    0.0006859577065952697,
                    0.0005333450480083265,
                    6.72e-05
                ],
                [
                    0.0008399999999999999,
                    0.0005207450480083266,
                    0
                ],
                [
                    0.0008399999999999999,
                    0.0005207450480083266,
                    6.72e-05
                ]
            ]
        ],
        "19": [
            [
                [
                    0.00015370286675591284,
                    0.0006384686899895918,
                    0
                ],
                [
                    0.00015370286675591284,
                    0.0006384686899895918,
                    6.72e-05
                ],
                [
                    0,
                    0.0006510686899895918,
                    0
                ],
                [
                    0,
                    0.0006510686899895918,
                    6.72e-05
                ]
            ],
            [
                [
                    0,
                    0.0006929313100104081,
                    0
                ],
                [
                    0,
                    0.0006929313100104081,
                    6.72e-05
                ],
                [
                    0.00015709713324408713,
                    0.0006813313100104081,
                    0
                ],
                [
                    0.00015709713324408713,
                    0.0006813313100104081,
                    6.72e-05
                ]
            ]
        ],
        "20": [
            [
                [
                    0.0003234,
                    0.0006384,
                    0
                ],
                [
                    0.0003234,
                    0.0006384,
                    6.72e-05
                ],
                [
                    0.00014279999999999997,
                    0.0006384,
                    0
                ],
                [
                    0.00014279999999999997,
                    0.0006384,
                    6.72e-05
                ]
            ],
            [
                [
                    0.00014279999999999997,
                    0.0006804,
                    0
                ],
                [
                    0.00014279999999999997,
                    0.0006804,
                    6.72e-05
                ],
                [
                    0.0003234,
                    0.0006804,
                    0
                ],
                [
                    0.0003234,
                    0.0006804,
                    6.72e-05
                ]
            ]
        ],
        "21": [
            [
                [
                    0.0004914,
                    0.0006426,
                    0
                ],
                [
                    0.0004914,
                    0.0006426,
                    6.72e-05
                ],
                [
                    0.0003234,
                    0.0006426,
                    0
                ],
                [
                    0.0003234,
                    0.0006426,
                    6.72e-05
                ]
            ],
            [
                [
                    0.0003234,
                    0.0006762,
                    0
                ],
                [
                    0.0003234,
                    0.0006762,
                    6.72e-05
                ],
                [
                    0.0004914,
                    0.0006762,
                    0
                ],
                [
                    0.0004914,
                    0.0006762,
                    6.72e-05
                ]
            ]
        ],
        "22": [
            [
                [
                    0.000672,
                    0.0006468,
                    0
                ],
                [
                    0.000672,
                    0.0006468,
                    6.72e-05
                ],
                [
                    0.0004914,
                    0.0006468,
                    0
                ],
                [
                    0.0004914,
                    0.0006468,
                    6.72e-05
                ]
            ],
            [
                [
                    0.0004914,
                    0.000672,
                    0
                ],
                [
                    0.0004914,
                    0.000672,
                    6.72e-05
                ],
                [
                    0.000672,
                    0.000672,
                    0
                ],
                [
                    0.000672,
                    0.000672,
                    6.72e-05
                ]
            ]
        ],
        "23": [
            [
                [
                    0.0008399999999999999,
                    0.0006510509228824393,
                    0
                ],
                [
                    0.0008399999999999999,
                    0.0006510509228824393,
                    6.72e-05
                ],
                [
                    0.0006608615635198298,
                    0.0006384509228824393,
                    0
                ],
                [
                    0.0006608615635198298,
                    0.0006384509228824393,
                    6.72e-05
                ]
            ],
            [
                [
                    0.0006579384364801702,
                    0.0006803490771175606,
                    0
                ],
                [
                    0.0006579384364801702,
                    0.0006803490771175606,
                    6.72e-05
                ],
                [
                    0.0008399999999999999,
                    0.0006929490771175606,
                    0
                ],
                [
                    0.0008399999999999999,
                    0.0006929490771175606,
                    6.72e-05
                ]
            ]
        ],
        "24": [
            [
                [
                    0.0001820615635198298,
                    0.0008316509228824393,
                    0
                ],
                [
                    0.0001820615635198298,
                    0.0008316509228824393,
                    6.72e-05
                ],
                [
                    0,
                    0.0008190509228824393,
                    0
                ],
                [
                    0,
                    0.0008190509228824393,
                    6.72e-05
                ]
            ],
            [
                [
                    0,
                    0.0008609490771175606,
                    0
                ],
                [
                    0,
                    0.0008609490771175606,
                    6.72e-05
                ],
                [
                    0.0001791384364801702,
                    0.0008735490771175605,
                    0
                ],
                [
                    0.0001791384364801702,
                    0.0008735490771175605,
                    6.72e-05
                ]
            ]
        ],
        "25": [
            [
                [
                    0.0003612,
                    0.0008399999999999999,
                    0
                ],
                [
                    0.0003612,
                    0.0008399999999999999,
                    6.72e-05
                ],
                [
                    0.00015539999999999998,
                    0.0008399999999999999,
                    0
                ],
                [
                    0.00015539999999999998,
                    0.0008399999999999999,
                    6.72e-05
                ]
            ],
            [
                [
                    0.00015539999999999998,
                    0.0008651999999999999,
                    0
                ],
                [
                    0.00015539999999999998,
                    0.0008651999999999999,
                    6.72e-05
                ],
                [
                    0.0003612,
                    0.0008651999999999999,
                    0
                ],
                [
                    0.0003612,
                    0.0008651999999999999,
                    6.72e-05
                ]
            ]
        ],
        "26": [
            [
                [
                    0.0006594,
                    0.0008106,
                    0
                ],
                [
                    0.0006594,
                    0.0008106,
                    6.72e-05
                ],
                [
                    0.0004914,
                    0.0008106,
                    0
                ],
                [
                    0.0004914,
                    0.0008106,
                    6.72e-05
                ]
            ],
            [
                [
                    0.0004914,
                    0.0008441999999999999,
                    0
                ],
                [
                    0.0004914,
                    0.0008441999999999999,
                    6.72e-05
                ],
                [
                    0.0006594,
                    0.0008441999999999999,
                    0
                ],
                [
                    0.0006594,
                    0.0008441999999999999,
                    6.72e-05
                ]
            ]
        ],
        "27": [
            [
                [
                    0.0008399999999999999,
                    0.0008232407383059515,
                    0
                ],
                [
                    0.0008399999999999999,
                    0.0008232407383059515,
                    6.72e-05
                ],
                [
                    0.0006605692508158638,
                    0.0008106407383059515,
                    0
                ],
                [
                    0.0006605692508158638,
                    0.0008106407383059515,
                    6.72e-05
                ]
            ],
            [
                [
                    0.0006582307491841362,
                    0.0008441592616940484,
                    0
                ],
                [
                    0.0006582307491841362,
                    0.0008441592616940484,
                    6.72e-05
                ],
                [
                    0.0008399999999999999,
                    0.0008567592616940484,
                    0
                ],
                [
                    0.0008399999999999999,
                    0.0008567592616940484,
                    6.72e-05
                ]
            ]
        ],
        "28": [
            [
                [
                    0.00036539999999999994,
                    0.0001974,
                    0
                ],
                [
                    0.00036539999999999994,
                    0.0001974,
                    6.72e-05
                ],
                [
                    0.00036539999999999994,
                    1.2599999999999998e-05,
                    0
                ],
                [
                    0.00036539999999999994,
                    1.2599999999999998e-05,
                    6.72e-05
                ]
            ],
            [
                [
                    0.0003318,
                    1.2599999999999998e-05,
                    0
                ],
                [
                    0.0003318,
                    1.2599999999999998e-05,
                    6.72e-05
                ],
                [
                    0.0003318,
                    0.0001974,
                    0
                ],
                [
                    0.0003318,
                    0.0001974,
                    6.72e-05
                ]
            ]
        ],
        "29": [
            [
                [
                    0.000535431785200267,
                    0.00019508598861559,
                    0
                ],
                [
                    0.000535431785200267,
                    0.00019508598861559,
                    6.72e-05
                ],
                [
                    0.0005080588869079285,
                    -1.4772898292338497e-05,
                    0
                ],
                [
                    0.0005080588869079285,
                    -1.4772898292338497e-05,
                    6.72e-05
                ]
            ],
            [
                [
                    0.0004747411130920715,
                    -1.0427101707661499e-05,
                    0
                ],
                [
                    0.0004747411130920715,
                    -1.0427101707661499e-05,
                    6.72e-05
                ],
                [
                    0.0005021140113844099,
                    0.00019943178520026702,
                    0
                ],
                [
                    0.0005021140113844099,
                    0.00019943178520026702,
                    6.72e-05
                ]
            ]
        ],
        "30": [
            [
                [
                    0.0006762,
                    0.00017219999999999998,
                    0
                ],
                [
                    0.0006762,
                    0.00017219999999999998,
                    6.72e-05
                ],
                [
                    0.0006762,
                    -2.9399999999999996e-05,
                    0
                ],
                [
                    0.0006762,
                    -2.9399999999999996e-05,
                    6.72e-05
                ]
            ],
            [
                [
                    0.0006426,
                    -2.9399999999999996e-05,
                    0
                ],
                [
                    0.0006426,
                    -2.9399999999999996e-05,
                    6.72e-05
                ],
                [
                    0.0006426,
                    0.00017219999999999998,
                    0
                ],
                [
                    0.0006426,
                    0.00017219999999999998,
                    6.72e-05
                ]
            ]
        ],
        "31": [
            [
                [
                    0.00019943178520026702,
                    0.00036308598861558997,
                    0
                ],
                [
                    0.00019943178520026702,
                    0.00036308598861558997,
                    6.72e-05
                ],
                [
                    0.00016988598861559,
                    0.00013656821479973296,
                    0
                ],
                [
                    0.00016988598861559,
                    0.00013656821479973296,
                    6.72e-05
                ]
            ],
            [
                [
                    0.00013656821479973296,
                    0.00014091401138440998,
                    0
                ],
                [
                    0.00013656821479973296,
                    0.00014091401138440998,
                    6.72e-05
                ],
                [
                    0.00016611401138441,
                    0.000367431785200267,
                    0
                ],
                [
                    0.00016611401138441,
                    0.000367431785200267,
                    6.72e-05
                ]
            ]
        ],
        "32": [
            [
                [
                    0.00034772994674726665,
                    0.00035,
                    0
                ],
                [
                    0.00034772994674726665,
                    0.00035,
                    6.72e-05
                ],
                [
                    0.00036928045473517664,
                    0.00018424949201209,
                    0
                ],
                [
                    0.00036928045473517664,
                    0.00018424949201209,
                    6.72e-05
                ]
            ],
            [
                [
                    0.0003279195452648233,
                    0.00017695050798791,
                    0
                ],
                [
                    0.0003279195452648233,
                    0.00017695050798791,
                    6.72e-05
                ],
                [
                    0.0003063690372769133,
                    0.0003404309627230867,
                    0
                ],
                [
                    0.0003063690372769133,
                    0.0003404309627230867,
                    6.72e-05
                ]
            ]
        ],
        "33": [
            [
                [
                    0.0005108639573978134,
                    0.0003428639573978133,
                    0
                ],
                [
                    0.0005108639573978134,
                    0.0003428639573978133,
                    6.72e-05
                ],
                [
                    0.0005331443637881414,
                    0.00018351959360967199,
                    0
                ],
                [
                    0.0005331443637881414,
                    0.00018351959360967199,
                    6.72e-05
                ]
            ],
            [
                [
                    0.0005000556362118586,
                    0.000177680406390328,
                    0
                ],
                [
                    0.0005000556362118586,
                    0.000177680406390328,
                    6.72e-05
                ],
                [
                    0.00047777522982153073,
                    0.00033702477017846934,
                    0
                ],
                [
                    0.00047777522982153073,
                    0.00033702477017846934,
                    6.72e-05
                ]
            ]
        ],
        "34": [
            [
                [
                    0.0003444,
                    0.0004914,
                    0
                ],
                [
                    0.0003444,
                    0.0004914,
                    6.72e-05
                ],
                [
                    0.0003444,
                    0.0003234,
                    0
                ],
                [
                    0.0003444,
                    0.0003234,
                    6.72e-05
                ]
            ],
            [
                [
                    0.0003024,
                    0.0003234,
                    0
                ],
                [
                    0.0003024,
                    0.0003234,
                    6.72e-05
                ],
                [
                    0.0003024,
                    0.0004914,
                    0
                ],
                [
                    0.0003024,
                    0.0004914,
                    6.72e-05
                ]
            ]
        ],
        "35": [
            [
                [
                    0.0005082,
                    0.0005082,
                    0
                ],
                [
                    0.0005082,
                    0.0005082,
                    6.72e-05
                ],
                [
                    0.0005082,
                    0.0003234,
                    0
                ],
                [
                    0.0005082,
                    0.0003234,
                    6.72e-05
                ]
            ],
            [
                [
                    0.00047460000000000004,
                    0.0003234,
                    0
                ],
                [
                    0.00047460000000000004,
                    0.0003234,
                    6.72e-05
                ],
                [
                    0.00047460000000000004,
                    0.0005082,
                    0
                ],
                [
                    0.00047460000000000004,
                    0.0005082,
                    6.72e-05
                ]
            ]
        ],
        "36": [
            [
                [
                    0.0007013999999999999,
                    0.0005334,
                    0
                ],
                [
                    0.0007013999999999999,
                    0.0005334,
                    6.72e-05
                ],
                [
                    0.0007013999999999999,
                    0.00034859999999999996,
                    0
                ],
                [
                    0.0007013999999999999,
                    0.00034859999999999996,
                    6.72e-05
                ]
            ],
            [
                [
                    0.0006678,
                    0.00034859999999999996,
                    0
                ],
                [
                    0.0006678,
                    0.00034859999999999996,
                    6.72e-05
                ],
                [
                    0.0006678,
                    0.0005334,
                    0
                ],
                [
                    0.0006678,
                    0.0005334,
                    6.72e-05
                ]
            ]
        ],
        "37": [
            [
                [
                    0.0003402,
                    0.0006762,
                    0
                ],
                [
                    0.0003402,
                    0.0006762,
                    6.72e-05
                ],
                [
                    0.0003402,
                    0.0004914,
                    0
                ],
                [
                    0.0003402,
                    0.0004914,
                    6.72e-05
                ]
            ],
            [
                [
                    0.0003066,
                    0.0004914,
                    0
                ],
                [
                    0.0003066,
                    0.0004914,
                    6.72e-05
                ],
                [
                    0.0003066,
                    0.0006762,
                    0
                ],
                [
                    0.0003066,
                    0.0006762,
                    6.72e-05
                ]
            ]
        ],
        "38": [
            [
                [
                    0.0005082,
                    0.0006594,
                    0
                ],
                [
                    0.0005082,
                    0.0006594,
                    6.72e-05
                ],
                [
                    0.0005082,
                    0.00047460000000000004,
                    0
                ],
                [
                    0.0005082,
                    0.00047460000000000004,
                    6.72e-05
                ]
            ],
            [
                [
                    0.00047460000000000004,
                    0.00047460000000000004,
                    0
                ],
                [
                    0.00047460000000000004,
                    0.00047460000000000004,
                    6.72e-05
                ],
                [
                    0.00047460000000000004,
                    0.0006594,
                    0
                ],
                [
                    0.00047460000000000004,
                    0.0006594,
                    6.72e-05
                ]
            ]
        ],
        "39": [
            [
                [
                    0.0006800804547351766,
                    0.00066304949201209,
                    0
                ],
                [
                    0.0006800804547351766,
                    0.00066304949201209,
                    6.72e-05
                ],
                [
                    0.0007052804547351766,
                    0.00052024949201209,
                    0
                ],
                [
                    0.0007052804547351766,
                    0.00052024949201209,
                    6.72e-05
                ]
            ],
            [
                [
                    0.0006639195452648233,
                    0.00051295050798791,
                    0
                ],
                [
                    0.0006639195452648233,
                    0.00051295050798791,
                    6.72e-05
                ],
                [
                    0.0006387195452648234,
                    0.00065575050798791,
                    0
                ],
                [
                    0.0006387195452648234,
                    0.00065575050798791,
                    6.72e-05
                ]
            ]
        ],
        "40": [
            [
                [
                    0.0003652588869079285,
                    0.0008504271017076615,
                    0
                ],
                [
                    0.0003652588869079285,
                    0.0008504271017076615,
                    6.72e-05
                ],
                [
                    0.00033788598861559,
                    0.000640568214799733,
                    0
                ],
                [
                    0.00033788598861559,
                    0.000640568214799733,
                    6.72e-05
                ]
            ],
            [
                [
                    0.000304568214799733,
                    0.0006449140113844099,
                    0
                ],
                [
                    0.000304568214799733,
                    0.0006449140113844099,
                    6.72e-05
                ],
                [
                    0.00033194111309207145,
                    0.0008547728982923384,
                    0
                ],
                [
                    0.00033194111309207145,
                    0.0008547728982923384,
                    6.72e-05
                ]
            ]
        ],
        "41": [
            [
                [
                    0.0006762,
                    0.0008273999999999999,
                    0
                ],
                [
                    0.0006762,
                    0.0008273999999999999,
                    6.72e-05
                ],
                [
                    0.0006762,
                    0.0006426,
                    0
                ],
                [
                    0.0006762,
                    0.0006426,
                    6.72e-05
                ]
            ],
            [
                [
                    0.0006426,
                    0.0006426,
                    0
                ],
                [
                    0.0006426,
                    0.0006426,
                    6.72e-05
                ],
                [
                    0.0006426,
                    0.0008273999999999999,
                    0
                ],
                [
                    0.0006426,
                    0.0008273999999999999,
                    6.72e-05
                ]
            ]
        ]
    }
}